michaelPanSqlLib/__init__.py
michaelPanSqlLib/mongo_database.py
michaelPanSqlLib/mysql_database.py
michaelPanSqlLib/postgresql_database.py
michaelPanSqlLib/redis_database.py
michaelPanSqlLib-1.0.0.dist-info/LICENSE
michaelPanSqlLib-1.0.0.dist-info/METADATA
michaelPanSqlLib-1.0.0.dist-info/WHEEL
michaelPanSqlLib-1.0.0.dist-info/top_level.txt
michaelPanSqlLib-1.0.0.dist-info/RECORD
