Metadata-Version: 2.1
Name: michaelPanSqlLib
Version: 1.0.0
Summary: sql general method
Author: chuntong pan
Author-email: panzhang1314@gmail.com
Platform: all
Classifier: Programming Language :: Python :: 3
Classifier: License :: OSI Approved :: MIT License
Classifier: Operating System :: OS Independent
License-File: LICENSE
Requires-Dist: pymysql
Requires-Dist: michaelPanPrintLib
Requires-Dist: pymongo
Requires-Dist: redis
Requires-Dist: psycopg2
